cmem_cmemc/__init__.py
cmem_cmemc/_cmemc.zsh
cmem_cmemc/cli.py
cmem_cmemc/command.py
cmem_cmemc/command_group.py
cmem_cmemc/commands/__init__.py
cmem_cmemc/commands/acl.py
cmem_cmemc/commands/admin.py
cmem_cmemc/commands/client.py
cmem_cmemc/commands/config.py
cmem_cmemc/commands/dataset.py
cmem_cmemc/commands/file.py
cmem_cmemc/commands/graph.py
cmem_cmemc/commands/graph_imports.py
cmem_cmemc/commands/graph_insights.py
cmem_cmemc/commands/manual.py
cmem_cmemc/commands/metrics.py
cmem_cmemc/commands/migration.py
cmem_cmemc/commands/project.py
cmem_cmemc/commands/python.py
cmem_cmemc/commands/query.py
cmem_cmemc/commands/scheduler.py
cmem_cmemc/commands/store.py
cmem_cmemc/commands/user.py
cmem_cmemc/commands/validation.py
cmem_cmemc/commands/variable.py
cmem_cmemc/commands/vocabulary.py
cmem_cmemc/commands/workflow.py
cmem_cmemc/commands/workspace.py
cmem_cmemc/completion.py
cmem_cmemc/config_parser.py
cmem_cmemc/constants.py
cmem_cmemc/context.py
cmem_cmemc/exceptions.py
cmem_cmemc/manual_helper/__init__.py
cmem_cmemc/manual_helper/graph.py
cmem_cmemc/manual_helper/multi_page.py
cmem_cmemc/manual_helper/single_page.py
cmem_cmemc/migrations/__init__.py
cmem_cmemc/migrations/abc.py
cmem_cmemc/migrations/access_conditions_243.py
cmem_cmemc/migrations/bootstrap_data.py
cmem_cmemc/migrations/remove_noop_triple_251.py
cmem_cmemc/migrations/shapes_widget_integrations_243.py
cmem_cmemc/migrations/sparql_query_texts_242.py
cmem_cmemc/migrations/workspace_configurations.py
cmem_cmemc/object_list.py
cmem_cmemc/parameter_types/__init__.py
cmem_cmemc/parameter_types/path.py
cmem_cmemc/placeholder.py
cmem_cmemc/smart_path/__init__.py
cmem_cmemc/smart_path/clients/__init__.py
cmem_cmemc/smart_path/clients/http.py
cmem_cmemc/string_processor.py
cmem_cmemc/title_helper.py
cmem_cmemc/utils.py
cmem_cmemc-25.6.0.dist-info/METADATA
cmem_cmemc-25.6.0.dist-info/WHEEL
cmem_cmemc-25.6.0.dist-info/entry_points.txt
cmem_cmemc-25.6.0.dist-info/licenses/LICENSE
cmem_cmemc-25.6.0.dist-info/RECORD
