Metadata-Version: 2.4
Name: cmem-cmemc
Version: 25.6.0
Summary: Command line client for eccenca Corporate Memory
License: Apache-2.0
License-File: LICENSE
Author: eccenca
Author-email: cmempy-developer@eccenca.com
Requires-Python: >=3.10,<4.0
Classifier: Development Status :: 5 - Production/Stable
Classifier: Environment :: Console
Classifier: Intended Audience :: Customer Service
Classifier: Intended Audience :: Developers
Classifier: Intended Audience :: Information Technology
Classifier: Intended Audience :: Science/Research
Classifier: Intended Audience :: System Administrators
Classifier: License :: OSI Approved :: Apache Software License
Classifier: Natural Language :: English
Classifier: Operating System :: OS Independent
Classifier: Programming Language :: Python :: 3
Classifier: Programming Language :: Python :: 3.10
Classifier: Programming Language :: Python :: 3.11
Classifier: Programming Language :: Python :: 3.12
Classifier: Programming Language :: Python :: 3.13
Classifier: Programming Language :: Python :: 3.14
Classifier: Programming Language :: Python :: 3 :: Only
Classifier: Topic :: Database
Classifier: Topic :: Software Development :: Testing
Classifier: Topic :: Utilities
Requires-Dist: beautifulsoup4 (>=4.13.3,<5.0.0)
Requires-Dist: certifi (>=2024.2.2)
Requires-Dist: click (>=8.3.0,<9.0.0)
Requires-Dist: click-didyoumean (>=0.3.1,<0.4.0)
Requires-Dist: click-help-colors (>=0.9.4,<0.10.0)
Requires-Dist: cmem-cmempy (==25.4.0)
Requires-Dist: configparser (>=7.2.0,<8.0.0)
Requires-Dist: humanize (>=4.14.0,<5.0.0)
Requires-Dist: jinja2 (>=3.1.6,<4.0.0)
Requires-Dist: junit-xml (>=1.9,<2.0)
Requires-Dist: natsort (>=8.4.0,<9.0.0)
Requires-Dist: packaging (>=24.2,<25.0)
Requires-Dist: prometheus-client (>=0.21.1,<0.22.0)
Requires-Dist: pygments (>=2.19.1,<3.0.0)
Requires-Dist: pyjwt (>=2.10.1,<3.0.0)
Requires-Dist: python-dateutil (>=2.9.0.post0,<3.0.0)
Requires-Dist: requests (>=2.32.3,<3.0.0)
Requires-Dist: rich (>=14.0.0,<15.0.0)
Requires-Dist: six (>=1.17.0,<2.0.0)
Requires-Dist: smart-open (>=7.1.0,<8.0.0)
Requires-Dist: timeago (>=1.0.16,<2.0.0)
Requires-Dist: treelib (>=1.7.1,<2.0.0)
Requires-Dist: urllib3 (>=2.3.0,<3.0.0)
Project-URL: Homepage, https://eccenca.com/go/cmemc
